classcharts/__init__.py
classcharts/clients.py
classcharts-0.0.1.dist-info/METADATA
classcharts-0.0.1.dist-info/WHEEL
classcharts-0.0.1.dist-info/licenses/LICENSE
classcharts-0.0.1.dist-info/RECORD
